{
    "character": "yorick",
    "id": "1049911797",
    "result": "寒，如王者之触。",
    "detail": {
        "Data": {
            "TaskId": 2012843832,
            "Status": 2,
            "StatusStr": "success",
            "Result": "[0:0.000,0:2.918]  寒，如王者之触。\n",
            "ErrorMsg": "",
            "ResultDetail": [
                {
                    "FinalSentence": "寒，如王者之触。",
                    "SliceSentence": "寒 如 王者 之 触",
                    "StartMs": 0,
                    "EndMs": 2918,
                    "WordsNum": 5,
                    "Words": [
                        {
                            "Word": "寒",
                            "OffsetStartMs": 0,
                            "OffsetEndMs": 510
                        },
                        {
                            "Word": "如",
                            "OffsetStartMs": 510,
                            "OffsetEndMs": 690
                        },
                        {
                            "Word": "王者",
                            "OffsetStartMs": 690,
                            "OffsetEndMs": 1680
                        },
                        {
                            "Word": "之",
                            "OffsetStartMs": 1680,
                            "OffsetEndMs": 1890
                        },
                        {
                            "Word": "触",
                            "OffsetStartMs": 1890,
                            "OffsetEndMs": 2850
                        }
                    ],
                    "SpeechSpeed": 3.8,
                    "SpeakerId": 4294967295
                }
            ],
            "AudioDuration": 2.91875
        },
        "RequestId": "5b9d3dfb-ea60-49b3-aacd-6286283f3a3c"
    }
}