{
    "character": "poppy",
    "id": "536925866",
    "result": "哼哼。",
    "detail": {
        "Data": {
            "TaskId": 2012743293,
            "Status": 2,
            "StatusStr": "success",
            "Result": "[0:0.000,0:0.658]  哼哼。\n",
            "ErrorMsg": "",
            "ResultDetail": [
                {
                    "FinalSentence": "哼哼。",
                    "SliceSentence": "哼哼",
                    "StartMs": 0,
                    "EndMs": 658,
                    "WordsNum": 1,
                    "Words": [
                        {
                            "Word": "哼哼",
                            "OffsetStartMs": 0,
                            "OffsetEndMs": 570
                        }
                    ],
                    "SpeechSpeed": 4.6,
                    "SpeakerId": 4294967295
                }
            ],
            "AudioDuration": 0.658563
        },
        "RequestId": "b584677e-349d-490e-b7ea-9e620538d689"
    }
}