{
    "character": "pyke",
    "id": "1350214392",
    "result": "屠宰，感觉像是回家了一样。",
    "detail": {
        "Data": {
            "TaskId": 2012744958,
            "Status": 2,
            "StatusStr": "success",
            "Result": "[0:0.000,0:3.852]  屠宰，感觉像是回家了一样。\n",
            "ErrorMsg": "",
            "ResultDetail": [
                {
                    "FinalSentence": "屠宰，感觉像是回家了一样。",
                    "SliceSentence": "屠宰 感觉 像是 回家 了 一样",
                    "StartMs": 0,
                    "EndMs": 3852,
                    "WordsNum": 6,
                    "Words": [
                        {
                            "Word": "屠宰",
                            "OffsetStartMs": 0,
                            "OffsetEndMs": 690
                        },
                        {
                            "Word": "感觉",
                            "OffsetStartMs": 1320,
                            "OffsetEndMs": 1770
                        },
                        {
                            "Word": "像是",
                            "OffsetStartMs": 1770,
                            "OffsetEndMs": 2040
                        },
                        {
                            "Word": "回家",
                            "OffsetStartMs": 2040,
                            "OffsetEndMs": 2670
                        },
                        {
                            "Word": "了",
                            "OffsetStartMs": 2670,
                            "OffsetEndMs": 2790
                        },
                        {
                            "Word": "一样",
                            "OffsetStartMs": 2790,
                            "OffsetEndMs": 3390
                        }
                    ],
                    "SpeechSpeed": 4.4,
                    "SpeakerId": 4294967295
                }
            ],
            "AudioDuration": 3.852563
        },
        "RequestId": "7de2e36c-2be4-4f63-9d9a-15e42bb897a6"
    }
}