{
    "character": "irelia",
    "id": "352191791",
    "result": "为了逝者。",
    "detail": {
        "Data": {
            "TaskId": 2012581999,
            "Status": 2,
            "StatusStr": "success",
            "Result": "[0:0.000,0:1.199]  为了逝者。\n",
            "ErrorMsg": "",
            "ResultDetail": [
                {
                    "FinalSentence": "为了逝者。",
                    "SliceSentence": "为了 逝者",
                    "StartMs": 0,
                    "EndMs": 1199,
                    "WordsNum": 2,
                    "Words": [
                        {
                            "Word": "为了",
                            "OffsetStartMs": 0,
                            "OffsetEndMs": 270
                        },
                        {
                            "Word": "逝者",
                            "OffsetStartMs": 270,
                            "OffsetEndMs": 1140
                        }
                    ],
                    "SpeechSpeed": 5.0,
                    "SpeakerId": 4294967295
                }
            ],
            "AudioDuration": 1.19925
        },
        "RequestId": "44b771e1-1581-4066-810e-47553a575209"
    }
}