{
    "character": "caitlyn",
    "id": "246279715",
    "result": "你承认自己有罪，还真是慷慨。",
    "detail": {
        "Data": {
            "TaskId": 2012551534,
            "Status": 2,
            "StatusStr": "success",
            "Result": "[0:0.000,0:4.138]  你承认自己有罪，还真是慷慨。\n",
            "ErrorMsg": "",
            "ResultDetail": [
                {
                    "FinalSentence": "你承认自己有罪，还真是慷慨。",
                    "SliceSentence": "你 承认 自己 有罪 还 真是 慷慨",
                    "StartMs": 0,
                    "EndMs": 4138,
                    "WordsNum": 7,
                    "Words": [
                        {
                            "Word": "你",
                            "OffsetStartMs": 0,
                            "OffsetEndMs": 210
                        },
                        {
                            "Word": "承认",
                            "OffsetStartMs": 210,
                            "OffsetEndMs": 600
                        },
                        {
                            "Word": "自己",
                            "OffsetStartMs": 600,
                            "OffsetEndMs": 840
                        },
                        {
                            "Word": "有罪",
                            "OffsetStartMs": 840,
                            "OffsetEndMs": 1410
                        },
                        {
                            "Word": "还",
                            "OffsetStartMs": 1740,
                            "OffsetEndMs": 2040
                        },
                        {
                            "Word": "真是",
                            "OffsetStartMs": 2040,
                            "OffsetEndMs": 2490
                        },
                        {
                            "Word": "慷慨",
                            "OffsetStartMs": 2490,
                            "OffsetEndMs": 3480
                        }
                    ],
                    "SpeechSpeed": 4.6,
                    "SpeakerId": 4294967295
                }
            ],
            "AudioDuration": 4.138688
        },
        "RequestId": "e5a8c2cd-d160-42e8-9aa4-2bb395861761"
    }
}