{
    "character": "maokai",
    "id": "1848117617",
    "result": "连根拔起。",
    "detail": {
        "Data": {
            "TaskId": 2012721611,
            "Status": 2,
            "StatusStr": "success",
            "Result": "[0:0.000,0:2.606]  连根拔起。\n",
            "ErrorMsg": "",
            "ResultDetail": [
                {
                    "FinalSentence": "连根拔起。",
                    "SliceSentence": "连根拔起",
                    "StartMs": 0,
                    "EndMs": 2606,
                    "WordsNum": 1,
                    "Words": [
                        {
                            "Word": "连根拔起",
                            "OffsetStartMs": 0,
                            "OffsetEndMs": 1620
                        }
                    ],
                    "SpeechSpeed": 1.9,
                    "SpeakerId": 4294967295
                }
            ],
            "AudioDuration": 2.606063
        },
        "RequestId": "6ac92074-567b-486a-b9eb-5961ec14328b"
    }
}