{
    "character": "lucian",
    "id": "1272218509",
    "result": "小场面。",
    "detail": {
        "Data": {
            "TaskId": 2012717215,
            "Status": 2,
            "StatusStr": "success",
            "Result": "[0:0.000,0:2.113]  小场面。\n",
            "ErrorMsg": "",
            "ResultDetail": [
                {
                    "FinalSentence": "小场面。",
                    "SliceSentence": "小 场面",
                    "StartMs": 0,
                    "EndMs": 2113,
                    "WordsNum": 2,
                    "Words": [
                        {
                            "Word": "小",
                            "OffsetStartMs": 0,
                            "OffsetEndMs": 540
                        },
                        {
                            "Word": "场面",
                            "OffsetStartMs": 540,
                            "OffsetEndMs": 1500
                        }
                    ],
                    "SpeechSpeed": 2.4,
                    "SpeakerId": 4294967295
                }
            ],
            "AudioDuration": 2.113
        },
        "RequestId": "629fb2fe-3099-4378-a020-b48c350e14c8"
    }
}