{
    "character": "kayn",
    "id": "1428388182",
    "result": "哎呀。",
    "detail": {
        "Data": {
            "TaskId": 2012699576,
            "Status": 2,
            "StatusStr": "success",
            "Result": "[0:0.000,0:1.941]  哎呀。\n",
            "ErrorMsg": "",
            "ResultDetail": [
                {
                    "FinalSentence": "哎呀。",
                    "SliceSentence": "哎呀",
                    "StartMs": 0,
                    "EndMs": 1941,
                    "WordsNum": 1,
                    "Words": [
                        {
                            "Word": "哎呀",
                            "OffsetStartMs": 0,
                            "OffsetEndMs": 1350
                        }
                    ],
                    "SpeechSpeed": 1.5,
                    "SpeakerId": 4294967295
                }
            ],
            "AudioDuration": 1.941
        },
        "RequestId": "ccec12ad-4dd5-4e25-981e-fa0570d2bd72"
    }
}