{
    "character": "kayn",
    "id": "996552446",
    "result": "来呀。",
    "detail": {
        "Data": {
            "TaskId": 2012703260,
            "Status": 2,
            "StatusStr": "success",
            "Result": "[0:0.000,0:0.927]  来呀。\n",
            "ErrorMsg": "",
            "ResultDetail": [
                {
                    "FinalSentence": "来呀。",
                    "SliceSentence": "来呀",
                    "StartMs": 0,
                    "EndMs": 927,
                    "WordsNum": 1,
                    "Words": [
                        {
                            "Word": "来呀",
                            "OffsetStartMs": 0,
                            "OffsetEndMs": 750
                        }
                    ],
                    "SpeechSpeed": 3.2,
                    "SpeakerId": 4294967295
                }
            ],
            "AudioDuration": 0.927313
        },
        "RequestId": "6e2f62cf-5cfb-4be3-8788-0cb782cf4e44"
    }
}