{
    "character": "shen",
    "id": "1067183321",
    "result": "要步步为营。",
    "detail": {
        "Data": {
            "TaskId": 2012774104,
            "Status": 2,
            "StatusStr": "success",
            "Result": "[0:0.000,0:1.902]  要步步为营。\n",
            "ErrorMsg": "",
            "ResultDetail": [
                {
                    "FinalSentence": "要步步为营。",
                    "SliceSentence": "要 步步为营",
                    "StartMs": 0,
                    "EndMs": 1902,
                    "WordsNum": 2,
                    "Words": [
                        {
                            "Word": "要",
                            "OffsetStartMs": 0,
                            "OffsetEndMs": 240
                        },
                        {
                            "Word": "步步为营",
                            "OffsetStartMs": 240,
                            "OffsetEndMs": 1380
                        }
                    ],
                    "SpeechSpeed": 3.7,
                    "SpeakerId": 4294967295
                }
            ],
            "AudioDuration": 1.902188
        },
        "RequestId": "77516fe0-e59d-419c-85d9-7fa6388e8a61"
    }
}