{
    "character": "darius",
    "id": "1586054625",
    "result": "这无人可挡的武力。",
    "detail": {
        "Data": {
            "TaskId": 2012555831,
            "Status": 2,
            "StatusStr": "success",
            "Result": "[0:0.000,0:2.600]  这无人可挡的武力。\n",
            "ErrorMsg": "",
            "ResultDetail": [
                {
                    "FinalSentence": "这无人可挡的武力。",
                    "SliceSentence": "这 无人可挡 的 武力",
                    "StartMs": 0,
                    "EndMs": 2600,
                    "WordsNum": 4,
                    "Words": [
                        {
                            "Word": "这",
                            "OffsetStartMs": 0,
                            "OffsetEndMs": 90
                        },
                        {
                            "Word": "无人可挡",
                            "OffsetStartMs": 90,
                            "OffsetEndMs": 1230
                        },
                        {
                            "Word": "的",
                            "OffsetStartMs": 1230,
                            "OffsetEndMs": 1320
                        },
                        {
                            "Word": "武力",
                            "OffsetStartMs": 1320,
                            "OffsetEndMs": 2250
                        }
                    ],
                    "SpeechSpeed": 4.6,
                    "SpeakerId": 4294967295
                }
            ],
            "AudioDuration": 2.600625
        },
        "RequestId": "27535af0-66af-4337-b31f-e0f92f8cd49d"
    }
}