{
    "character": "jhin",
    "id": "1192222958",
    "result": "这部作品还缺点什么？",
    "detail": {
        "Data": {
            "TaskId": 2012684574,
            "Status": 2,
            "StatusStr": "success",
            "Result": "[0:0.000,0:3.249]  这部作品还缺点什么？\n",
            "ErrorMsg": "",
            "ResultDetail": [
                {
                    "FinalSentence": "这部作品还缺点什么？",
                    "SliceSentence": "这部 作品 还 缺点 什么",
                    "StartMs": 0,
                    "EndMs": 3249,
                    "WordsNum": 5,
                    "Words": [
                        {
                            "Word": "这部",
                            "OffsetStartMs": 0,
                            "OffsetEndMs": 240
                        },
                        {
                            "Word": "作品",
                            "OffsetStartMs": 240,
                            "OffsetEndMs": 930
                        },
                        {
                            "Word": "还",
                            "OffsetStartMs": 930,
                            "OffsetEndMs": 1200
                        },
                        {
                            "Word": "缺点",
                            "OffsetStartMs": 1200,
                            "OffsetEndMs": 1860
                        },
                        {
                            "Word": "什么",
                            "OffsetStartMs": 1860,
                            "OffsetEndMs": 2610
                        }
                    ],
                    "SpeechSpeed": 4.3,
                    "SpeakerId": 4294967295
                }
            ],
            "AudioDuration": 3.249063
        },
        "RequestId": "1b0bfc8d-870c-4b59-9245-69d8c53b13e5"
    }
}