{
    "character": "jhin",
    "id": "531148299",
    "result": "艺术应当震慑人心。",
    "detail": {
        "Data": {
            "TaskId": 2012686125,
            "Status": 2,
            "StatusStr": "success",
            "Result": "[0:0.000,0:4.320]  艺术应当震慑人心。\n",
            "ErrorMsg": "",
            "ResultDetail": [
                {
                    "FinalSentence": "艺术应当震慑人心。",
                    "SliceSentence": "艺术 应当 震慑 人心",
                    "StartMs": 0,
                    "EndMs": 4320,
                    "WordsNum": 4,
                    "Words": [
                        {
                            "Word": "艺术",
                            "OffsetStartMs": 0,
                            "OffsetEndMs": 1080
                        },
                        {
                            "Word": "应当",
                            "OffsetStartMs": 1350,
                            "OffsetEndMs": 1860
                        },
                        {
                            "Word": "震慑",
                            "OffsetStartMs": 1860,
                            "OffsetEndMs": 2490
                        },
                        {
                            "Word": "人心",
                            "OffsetStartMs": 2490,
                            "OffsetEndMs": 3390
                        }
                    ],
                    "SpeechSpeed": 2.8,
                    "SpeakerId": 4294967295
                }
            ],
            "AudioDuration": 6.054188
        },
        "RequestId": "2eede97c-a418-4ec0-93bd-d3d15955aef7"
    }
}