{
    "character": "akali",
    "id": "605022497",
    "result": "哼哼，你有血光之灾。",
    "detail": {
        "Data": {
            "TaskId": 2012539943,
            "Status": 2,
            "StatusStr": "success",
            "Result": "[0:0.000,0:2.749]  哼哼，你有血光之灾。\n",
            "ErrorMsg": "",
            "ResultDetail": [
                {
                    "FinalSentence": "哼哼，你有血光之灾。",
                    "SliceSentence": "哼哼 你有 血 光 之灾",
                    "StartMs": 0,
                    "EndMs": 2749,
                    "WordsNum": 5,
                    "Words": [
                        {
                            "Word": "哼哼",
                            "OffsetStartMs": 0,
                            "OffsetEndMs": 510
                        },
                        {
                            "Word": "你有",
                            "OffsetStartMs": 870,
                            "OffsetEndMs": 1320
                        },
                        {
                            "Word": "血",
                            "OffsetStartMs": 1320,
                            "OffsetEndMs": 1560
                        },
                        {
                            "Word": "光",
                            "OffsetStartMs": 1560,
                            "OffsetEndMs": 1800
                        },
                        {
                            "Word": "之灾",
                            "OffsetStartMs": 1800,
                            "OffsetEndMs": 2610
                        }
                    ],
                    "SpeechSpeed": 4.7,
                    "SpeakerId": 4294967295
                }
            ],
            "AudioDuration": 2.749813
        },
        "RequestId": "32e5555f-5ff5-4149-9b7b-aad697f022c1"
    }
}