{
    "character": "viktor",
    "id": "379630654",
    "result": "形态决定功能。",
    "detail": {
        "Data": {
            "TaskId": 2012814874,
            "Status": 2,
            "StatusStr": "success",
            "Result": "[0:0.000,0:2.477]  形态决定功能。\n",
            "ErrorMsg": "",
            "ResultDetail": [
                {
                    "FinalSentence": "形态决定功能。",
                    "SliceSentence": "形态 决定 功能",
                    "StartMs": 0,
                    "EndMs": 2477,
                    "WordsNum": 3,
                    "Words": [
                        {
                            "Word": "形态",
                            "OffsetStartMs": 0,
                            "OffsetEndMs": 810
                        },
                        {
                            "Word": "决定",
                            "OffsetStartMs": 810,
                            "OffsetEndMs": 1350
                        },
                        {
                            "Word": "功能",
                            "OffsetStartMs": 1350,
                            "OffsetEndMs": 2370
                        }
                    ],
                    "SpeechSpeed": 3.6,
                    "SpeakerId": 4294967295
                }
            ],
            "AudioDuration": 2.4775
        },
        "RequestId": "9712f04f-fe46-4705-aedb-34743910d416"
    }
}