{
    "character": "swain",
    "id": "1183073327",
    "result": "没有目的，就没有团结，而所有人生来都有同一个终点。",
    "detail": {
        "Data": {
            "TaskId": 2012783667,
            "Status": 2,
            "StatusStr": "success",
            "Result": "[0:0.000,0:7.616]  没有目的，就没有团结，而所有人生来都有同一个终点。\n",
            "ErrorMsg": "",
            "ResultDetail": [
                {
                    "FinalSentence": "没有目的，就没有团结，而所有人生来都有同一个终点。",
                    "SliceSentence": "没有 目的 就没 有 团结 而 所有人 生来 都有 同一个 终点",
                    "StartMs": 0,
                    "EndMs": 7616,
                    "WordsNum": 11,
                    "Words": [
                        {
                            "Word": "没有",
                            "OffsetStartMs": 0,
                            "OffsetEndMs": 420
                        },
                        {
                            "Word": "目的",
                            "OffsetStartMs": 420,
                            "OffsetEndMs": 1080
                        },
                        {
                            "Word": "就没",
                            "OffsetStartMs": 1080,
                            "OffsetEndMs": 1410
                        },
                        {
                            "Word": "有",
                            "OffsetStartMs": 1410,
                            "OffsetEndMs": 1620
                        },
                        {
                            "Word": "团结",
                            "OffsetStartMs": 1620,
                            "OffsetEndMs": 2580
                        },
                        {
                            "Word": "而",
                            "OffsetStartMs": 3150,
                            "OffsetEndMs": 3480
                        },
                        {
                            "Word": "所有人",
                            "OffsetStartMs": 3480,
                            "OffsetEndMs": 4200
                        },
                        {
                            "Word": "生来",
                            "OffsetStartMs": 4200,
                            "OffsetEndMs": 5160
                        },
                        {
                            "Word": "都有",
                            "OffsetStartMs": 5220,
                            "OffsetEndMs": 5730
                        },
                        {
                            "Word": "同一个",
                            "OffsetStartMs": 5730,
                            "OffsetEndMs": 6600
                        },
                        {
                            "Word": "终点",
                            "OffsetStartMs": 6600,
                            "OffsetEndMs": 7440
                        }
                    ],
                    "SpeechSpeed": 4.3,
                    "SpeakerId": 4294967295
                }
            ],
            "AudioDuration": 7.616375
        },
        "RequestId": "c8679a6b-65bc-4e22-983c-8251e9926072"
    }
}