{
    "character": "renata",
    "id": "1700293169",
    "result": "海克斯科竟有这本事吗？",
    "detail": {
        "Data": {
            "TaskId": 2012760052,
            "Status": 2,
            "StatusStr": "success",
            "Result": "[0:0.000,0:3.189]  海克斯科竟有这本事吗？\n",
            "ErrorMsg": "",
            "ResultDetail": [
                {
                    "FinalSentence": "海克斯科竟有这本事吗？",
                    "SliceSentence": "海克 斯科 竟有 这 本事 吗",
                    "StartMs": 0,
                    "EndMs": 3189,
                    "WordsNum": 6,
                    "Words": [
                        {
                            "Word": "海克",
                            "OffsetStartMs": 30,
                            "OffsetEndMs": 480
                        },
                        {
                            "Word": "斯科",
                            "OffsetStartMs": 480,
                            "OffsetEndMs": 870
                        },
                        {
                            "Word": "竟有",
                            "OffsetStartMs": 870,
                            "OffsetEndMs": 1230
                        },
                        {
                            "Word": "这",
                            "OffsetStartMs": 1230,
                            "OffsetEndMs": 1500
                        },
                        {
                            "Word": "本事",
                            "OffsetStartMs": 1500,
                            "OffsetEndMs": 2010
                        },
                        {
                            "Word": "吗",
                            "OffsetStartMs": 2010,
                            "OffsetEndMs": 2910
                        }
                    ],
                    "SpeechSpeed": 5.0,
                    "SpeakerId": 4294967295
                }
            ],
            "AudioDuration": 3.189688
        },
        "RequestId": "92004eb3-6ec0-4395-a55c-860bce54ea42"
    }
}