{
    "character": "tristana",
    "id": "193395683",
    "result": "哇哦。",
    "detail": {
        "Data": {
            "TaskId": 2012799229,
            "Status": 2,
            "StatusStr": "success",
            "Result": "[0:0.000,0:0.590]  哇哦。\n",
            "ErrorMsg": "",
            "ResultDetail": [
                {
                    "FinalSentence": "哇哦。",
                    "SliceSentence": "哇哦",
                    "StartMs": 0,
                    "EndMs": 590,
                    "WordsNum": 1,
                    "Words": [
                        {
                            "Word": "哇哦",
                            "OffsetStartMs": 0,
                            "OffsetEndMs": 450
                        }
                    ],
                    "SpeechSpeed": 5.1,
                    "SpeakerId": 4294967295
                }
            ],
            "AudioDuration": 0.590125
        },
        "RequestId": "07c39115-953f-4df1-8e18-0e6bceedd3e2"
    }
}