{
    "character": "sett",
    "id": "1720973791",
    "result": "有需求的地方就有供给。",
    "detail": {
        "Data": {
            "TaskId": 2012772717,
            "Status": 2,
            "StatusStr": "success",
            "Result": "[0:0.000,0:3.645]  有需求的地方就有供给。\n",
            "ErrorMsg": "",
            "ResultDetail": [
                {
                    "FinalSentence": "有需求的地方就有供给。",
                    "SliceSentence": "有 需求 的 地方 就有 供给",
                    "StartMs": 0,
                    "EndMs": 3645,
                    "WordsNum": 6,
                    "Words": [
                        {
                            "Word": "有",
                            "OffsetStartMs": 0,
                            "OffsetEndMs": 240
                        },
                        {
                            "Word": "需求",
                            "OffsetStartMs": 240,
                            "OffsetEndMs": 780
                        },
                        {
                            "Word": "的",
                            "OffsetStartMs": 780,
                            "OffsetEndMs": 870
                        },
                        {
                            "Word": "地方",
                            "OffsetStartMs": 870,
                            "OffsetEndMs": 1500
                        },
                        {
                            "Word": "就有",
                            "OffsetStartMs": 1530,
                            "OffsetEndMs": 1860
                        },
                        {
                            "Word": "供给",
                            "OffsetStartMs": 1860,
                            "OffsetEndMs": 2910
                        }
                    ],
                    "SpeechSpeed": 4.4,
                    "SpeakerId": 4294967295
                }
            ],
            "AudioDuration": 3.645563
        },
        "RequestId": "e014f8c7-4fef-48c8-8720-15ea835ba3e7"
    }
}