{
    "character": "kled",
    "id": "636781750",
    "result": "团战不一定非要一团人才能打。",
    "detail": {
        "Data": {
            "TaskId": 2012708844,
            "Status": 2,
            "StatusStr": "success",
            "Result": "[0:0.000,0:3.490]  团战不一定非要一团人才能打。\n",
            "ErrorMsg": "",
            "ResultDetail": [
                {
                    "FinalSentence": "团战不一定非要一团人才能打。",
                    "SliceSentence": "团战 不一定 非要 一团 人才 能 打",
                    "StartMs": 0,
                    "EndMs": 3490,
                    "WordsNum": 7,
                    "Words": [
                        {
                            "Word": "团战",
                            "OffsetStartMs": 0,
                            "OffsetEndMs": 660
                        },
                        {
                            "Word": "不一定",
                            "OffsetStartMs": 840,
                            "OffsetEndMs": 1290
                        },
                        {
                            "Word": "非要",
                            "OffsetStartMs": 1290,
                            "OffsetEndMs": 1710
                        },
                        {
                            "Word": "一团",
                            "OffsetStartMs": 1710,
                            "OffsetEndMs": 2220
                        },
                        {
                            "Word": "人才",
                            "OffsetStartMs": 2220,
                            "OffsetEndMs": 2580
                        },
                        {
                            "Word": "能",
                            "OffsetStartMs": 2580,
                            "OffsetEndMs": 2730
                        },
                        {
                            "Word": "打",
                            "OffsetStartMs": 2730,
                            "OffsetEndMs": 3240
                        }
                    ],
                    "SpeechSpeed": 5.7,
                    "SpeakerId": 4294967295
                }
            ],
            "AudioDuration": 3.490188
        },
        "RequestId": "70245cdb-c35b-44d8-a1ae-52c400a605f5"
    }
}