{
    "character": "graves",
    "id": "37720350",
    "result": "哼哼。",
    "detail": {
        "Data": {
            "TaskId": 2012573628,
            "Status": 2,
            "StatusStr": "success",
            "Result": "[0:0.000,0:0.909]  哼哼。\n",
            "ErrorMsg": "",
            "ResultDetail": [
                {
                    "FinalSentence": "哼哼。",
                    "SliceSentence": "哼哼",
                    "StartMs": 0,
                    "EndMs": 909,
                    "WordsNum": 1,
                    "Words": [
                        {
                            "Word": "哼哼",
                            "OffsetStartMs": 0,
                            "OffsetEndMs": 840
                        }
                    ],
                    "SpeechSpeed": 3.3,
                    "SpeakerId": 4294967295
                }
            ],
            "AudioDuration": 0.909063
        },
        "RequestId": "fe3100b1-1a51-4525-96c7-1860e3f26b7a"
    }
}