{
    "character": "aphelios",
    "id": "1234848948",
    "result": "信仰的力量。",
    "detail": {
        "Data": {
            "TaskId": 2012542914,
            "Status": 2,
            "StatusStr": "success",
            "Result": "[0:0.000,0:4.240]  信仰的力量。\n",
            "ErrorMsg": "",
            "ResultDetail": [
                {
                    "FinalSentence": "信仰的力量。",
                    "SliceSentence": "信仰 的 力量",
                    "StartMs": 0,
                    "EndMs": 4240,
                    "WordsNum": 3,
                    "Words": [
                        {
                            "Word": "信仰",
                            "OffsetStartMs": 810,
                            "OffsetEndMs": 1380
                        },
                        {
                            "Word": "的",
                            "OffsetStartMs": 1380,
                            "OffsetEndMs": 1470
                        },
                        {
                            "Word": "力量",
                            "OffsetStartMs": 1470,
                            "OffsetEndMs": 1950
                        }
                    ],
                    "SpeechSpeed": 1.9,
                    "SpeakerId": 4294967295
                }
            ],
            "AudioDuration": 5.924063
        },
        "RequestId": "3e69a241-9159-4592-8875-231a969448d3"
    }
}